lavaclient/__init__.py
lavaclient/_version.py
lavaclient/cli.py
lavaclient/client.py
lavaclient/constants.py
lavaclient/error.py
lavaclient/identity.py
lavaclient/log.py
lavaclient/util.py
lavaclient/validators.py
lavaclient/api/__init__.py
lavaclient/api/clusters.py
lavaclient/api/credentials.py
lavaclient/api/distros.py
lavaclient/api/flavors.py
lavaclient/api/limits.py
lavaclient/api/nodes.py
lavaclient/api/resource.py
lavaclient/api/response.py
lavaclient/api/scripts.py
lavaclient/api/stacks.py
lavaclient/api/workloads.py
lavaclient-0.3.7.dist-info/DESCRIPTION.rst
lavaclient-0.3.7.dist-info/entry_points.txt
lavaclient-0.3.7.dist-info/METADATA
lavaclient-0.3.7.dist-info/metadata.json
lavaclient-0.3.7.dist-info/pbr.json
lavaclient-0.3.7.dist-info/RECORD
lavaclient-0.3.7.dist-info/top_level.txt
lavaclient-0.3.7.dist-info/WHEEL
