Metadata-Version: 2.0
Name: lavaclient
Version: 0.3.7
Summary: Client library for Rackspace Cloud Big Data API
Home-page: https://github.com/rackerlabs/python-lavaclient
Author: Rackspace
Author-email: UNKNOWN
License: Apache
Download-URL: https://github.com/rackerlabs/python-lavaclient/tarball/0.3.7
Platform: UNKNOWN
Classifier: Development Status :: 4 - Beta
Classifier: Intended Audience :: Developers
Classifier: Intended Audience :: Information Technology
Classifier: License :: OSI Approved :: Apache Software License
Classifier: Operating System :: OS Independent
Classifier: Programming Language :: Python
Requires-Dist: requests (>=2.5.1)
Requires-Dist: six (>=1.9.0)
Requires-Dist: python-dateutil (>=2.4.2)
Requires-Dist: figgis (>=1.6.2)
Requires-Dist: pysocks (>=1.5.4)
Requires-Dist: prettytable (>=0.7.2)
